omero/plugins/democleanup.py
omero_demo_cleanup/__init__.py
omero_demo_cleanup/cli.py
omero_demo_cleanup/library.py
omero_demo_cleanup-0.2.1.dist-info/LICENSE.txt
omero_demo_cleanup-0.2.1.dist-info/METADATA
omero_demo_cleanup-0.2.1.dist-info/WHEEL
omero_demo_cleanup-0.2.1.dist-info/top_level.txt
omero_demo_cleanup-0.2.1.dist-info/zip-safe
omero_demo_cleanup-0.2.1.dist-info/RECORD
