Metadata-Version: 2.1
Name: omero-demo-cleanup
Version: 0.2.1
Summary: Plugin for managing the disk space on the demo server.
Home-page: https://github.com/ome/omero-demo-cleanup/
Author: The Open Microscopy Team
Author-email: 
Keywords: OMERO.CLI,plugin
Classifier: Development Status :: 4 - Beta
Classifier: Environment :: Plugins
Classifier: Intended Audience :: Developers
Classifier: Intended Audience :: End Users/Desktop
Classifier: Intended Audience :: Information Technology
Classifier: License :: OSI Approved :: GNU General Public License v2 or later (GPLv2+)
Classifier: Natural Language :: English
Classifier: Operating System :: OS Independent
Classifier: Programming Language :: Python :: 3
Classifier: Topic :: Software Development :: Libraries :: Python Modules
Requires-Python: >=3.6
License-File: LICENSE.txt
Requires-Dist: omero-py (>=5.6.0)
